qalsadi/__init__.py
qalsadi/analex.py
qalsadi/analex_const.py
qalsadi/cache.py
qalsadi/cache_codernity.py
qalsadi/cache_factory.py
qalsadi/cache_pickle.py
qalsadi/cache_pickledb.py
qalsadi/coder.py
qalsadi/custom_dictionary.py
qalsadi/dictword.py
qalsadi/disambig.py
qalsadi/disambig_const.py
qalsadi/genAffixes.py
qalsadi/genalex.py
qalsadi/lemmatizer.py
qalsadi/noun_affixer.py
qalsadi/print_debug.py
qalsadi/stem_noun.py
qalsadi/stem_noun_const.py
qalsadi/stem_pounct_const.py
qalsadi/stem_stop.py
qalsadi/stem_stopwords_const.py
qalsadi/stem_unknown.py
qalsadi/stem_unknown_const.py
qalsadi/stem_verb.py
qalsadi/stem_verb_const.py
qalsadi/stemmedaffix.py
qalsadi/stemmedword.py
qalsadi/stemnode.py
qalsadi/stop_affixer.py
qalsadi/stopwords.py
qalsadi/templater.py
qalsadi/wordcase.py
qalsadi/data/custom_dictionary.sqlite
qalsadi-0.5.dist-info/METADATA
qalsadi-0.5.dist-info/WHEEL
qalsadi-0.5.dist-info/top_level.txt
qalsadi-0.5.dist-info/RECORD
