Metadata-Version: 2.1
Name: qalsadi
Version: 0.5
Summary: Qalsadi Arabic Morphological Analyzer and lemmatizer for Python
Home-page: http://qalsadi.sourceforge.net/
Author: Taha Zerrouki
Author-email: taha.zerrouki@gmail .com
License: GPL
Platform: UNKNOWN
Classifier: Development Status :: 5 - Production/Stable
Classifier: Natural Language :: Arabic
Classifier: Intended Audience :: Developers
Classifier: Operating System :: OS Independent
Classifier: Programming Language :: Python
Classifier: Topic :: Text Processing :: Linguistic
Requires-Dist: Arabic-Stopwords (>=0.4.2)
Requires-Dist: alyahmor (>=0.2)
Requires-Dist: arramooz-pysqlite (>=0.4.2)
Requires-Dist: codernitydb3
Requires-Dist: libqutrub (>=1.2.3)
Requires-Dist: mysam-tagmanager (>=0.3.3)
Requires-Dist: naftawayh (>=0.3)
Requires-Dist: pickledb (>=0.9.2)
Requires-Dist: pyarabic (>=0.6.7)
Requires-Dist: tashaphyne (>=0.3.4.1)
